Encryption/CaesarCipher.py
Encryption/Encoders.py
Encryption/MorseCoder.py
Encryption/PigLatin.py
Encryption/Vigenere.py
Encryption/__init__.py
Encryption-0.0.1.dist-info/LICENSE
Encryption-0.0.1.dist-info/METADATA
Encryption-0.0.1.dist-info/WHEEL
Encryption-0.0.1.dist-info/top_level.txt
Encryption-0.0.1.dist-info/RECORD
